{
  "cli": {
    "version": ">= 12.0.0",
    "appVersionSource": "local"
  },
  "build": {
    "development": {
      "developmentClient": true,
      "distribution": "internal",
      "ios": {}
    },
    "preview": {
      "distribution": "internal",
      "ios": {}
    },
    "production": {
      "ios": {
        "distribution": "store",
        "buildConfiguration": "Release",
        "image": "latest",
        "node": "20.18.0"
      }
    }
  },
  "submit": {
    "production": {
      "ios": {
        "ascAppId": "6749607856"
      }
    }
  }
} 